pysamsungrac/__init__.py
pysamsungrac/__init__.pyc
pysamsungrac/ac14k_m.pem
pysamsungrac/exceptions.py
pysamsungrac/network.py
pysamsungrac/samsungrac.py
pysamsungrac/__pycache__/__init__.cpython-37.pyc
pysamsungrac/__pycache__/__init__.cpython-38.pyc
pysamsungrac/__pycache__/exceptions.cpython-38.pyc
pysamsungrac/__pycache__/network.cpython-38.pyc
pysamsungrac/__pycache__/samsungrac.cpython-37.pyc
pysamsungrac/__pycache__/samsungrac.cpython-38.pyc
pysamsungrac-0.1.0.data/scripts/samsungrac.py
pysamsungrac-0.1.0.dist-info/LICENSE.txt
pysamsungrac-0.1.0.dist-info/METADATA
pysamsungrac-0.1.0.dist-info/WHEEL
pysamsungrac-0.1.0.dist-info/top_level.txt
pysamsungrac-0.1.0.dist-info/RECORD
