Metadata-Version: 2.1
Name: pysamsungrac
Version: 0.1.0
Summary: Control your Samsung Air Conditioner
Home-page: https://github.com/ishioni/pysamsungrac
Author: pmaksymiuk
Author-email: piotr.maksymiuk@movishell.pl
License: GPL3
Platform: UNKNOWN
Classifier: Environment :: Console
Classifier: License :: OSI Approved :: GNU General Public License v3 (GPLv3)
Classifier: Development Status :: 3 - Alpha
Classifier: Programming Language :: Python
Classifier: Programming Language :: Python :: 3
Classifier: Programming Language :: Python :: 3 :: Only
Classifier: Programming Language :: Python :: 3.6
Classifier: Programming Language :: Python :: 3.7
Classifier: Programming Language :: Python :: 3.8
Requires-Dist: aiohttp
